pydeeplator/__init__.py
pydeeplator/_version.py
pydeeplator/deepL.py
pydeeplator-0.0.2.dist-info/LICENSE
pydeeplator-0.0.2.dist-info/METADATA
pydeeplator-0.0.2.dist-info/WHEEL
pydeeplator-0.0.2.dist-info/top_level.txt
pydeeplator-0.0.2.dist-info/RECORD
