Metadata-Version: 2.1
Name: pydeeplator
Version: 0.0.2
Summary: Unofficial DeepL Translator API
Home-page: https://github.com/sunhailin-Leo/deepL-translator-api
Author: sunhailin-Leo
Author-email: 379978424@qq.com
License: MIT
Keywords: DeepL,pydeeplator
Platform: UNKNOWN
Classifier: Development Status :: 4 - Beta
Classifier: Environment :: Console
Classifier: Intended Audience :: Developers
Classifier: License :: OSI Approved :: MIT License
Classifier: Operating System :: OS Independent
Classifier: Programming Language :: Python
Classifier: Programming Language :: Python :: 3.6
Classifier: Programming Language :: Python :: 3.7
Classifier: Programming Language :: Python :: 3.8
Classifier: Topic :: Software Development :: Libraries
Requires-Dist: requests
